[{"link":"https:\/\/www.hellomagazine.com\/film\/732170\/jenna-bush-hager-double-celebrate-today-show-unveils-secret-project\/","title":"Jenna Bush Hager marks double celebration on today as she unveils secret project","ch":"HELLO! Latest news feed","date":1732551864,"image":"","audio":""},{"link":"https:\/\/www.hellomagazine.com\/hfm\/fashion-trends\/732100\/dua-lipa-sacai-t-shirt-dress-malaysia\/","title":"Dua Lipa nails T-shirt dress and knee-high boots pairing","ch":"HELLO! Latest news feed","date":1732551660,"image":"","audio":""},{"link":"https:\/\/www.hellomagazine.com\/royalty\/731512\/wolf-hall-right-royal-podcast-episode\/","title":"A Right Royal Podcast: Wolf Hall's ultimate fact vs fiction, Christmas at Windsor Castle and more","ch":"HELLO! Latest news feed","date":1732551209,"image":"","audio":""},{"link":"https:\/\/www.hellomagazine.com\/hfm\/beauty-trends\/732123\/kylie-jenner-step-by-step-soft-glam-makeup-routine\/","title":"Kylie Jenner 'soft-glam' makeup routine is easier to re-create than you think","ch":"HELLO! Latest news feed","date":1732550748,"image":"","audio":""},{"link":"https:\/\/www.hellomagazine.com\/healthandbeauty\/732145\/queen-camilla-princess-kate-inspired-makeover\/","title":"Queen Camilla's 'fierce' transformation to look just like Princess Kate","ch":"HELLO! Latest news feed","date":1732550494,"image":"","audio":""},{"link":"https:\/\/www.youtube.com\/watch?v=jPp3eDY6giQ","title":"Ashley Banjo: \u2018The Best Self-Care Is My Kids\u2019 | Loose Women","ch":"Loose Women","date":1732550430,"image":"https:\/\/i3.ytimg.com\/vi\/jPp3eDY6giQ\/hqdefault.jpg","audio":""},{"link":"https:\/\/www.entertainmentdaily.com\/tv\/rebekah-vardy-coleen-rooney-im-a-celebrity-compliments-trial\/","title":"Rebekah Vardy gushes over Coleen Rooney in I\u2019m A Celebrity trial","ch":"Entertainment Daily","date":1732547772,"image":"https:\/\/cdn.entertainmentdaily.com\/2021\/01\/25101916\/cropped-logo-512-32x32.png","audio":""},{"link":"https:\/\/vipmagazine.ie\/a-sweet-shop-for-your-nails-has-just-opened-in-dundrum-town-centre\/","title":"A sweet shop for your nails has just opened in Dundrum Town Centre","ch":"VIP Magazine","date":1732546352,"image":"https:\/\/vip-uploads.s3.amazonaws.com\/uploads\/2019\/09\/favicon-vip.png","audio":""},{"link":"https:\/\/www.youtube.com\/watch?v=WUcKt-0fLEw","title":"Strictly Controversy: Should Pete Wicks Have Left? | Loose Women","ch":"Loose Women","date":1732545024,"image":"https:\/\/i4.ytimg.com\/vi\/WUcKt-0fLEw\/hqdefault.jpg","audio":""},{"link":"https:\/\/www.bbc.com\/news\/articles\/c0lpr6e8rwgo","title":"Best-selling novelist Barbara Taylor Bradford dies","ch":"BBC News","date":1732544950,"image":"https:\/\/ichef.bbci.co.uk\/ace\/standard\/240\/cpsprodpb\/0641\/live\/21ff5d80-ab28-11ef-a4fe-a3e9a6c5d640.jpg","audio":""},{"link":"https:\/\/www.entertainmentdaily.com\/soaps\/coronation-street-kill-off-debbie-webster-40-years\/","title":"Coronation Street to \u2018kill off\u2019 Debbie Webster after 40 years","ch":"Entertainment Daily","date":1732544933,"image":"https:\/\/cdn.entertainmentdaily.com\/2021\/01\/25101916\/cropped-logo-512-32x32.png","audio":""},{"link":"https:\/\/www.bbc.com\/news\/articles\/cgl47nddn1wo","title":"Band Aid star defends song as megamix is released","ch":"BBC News","date":1732544291,"image":"https:\/\/ichef.bbci.co.uk\/ace\/standard\/240\/cpsprodpb\/ee39\/live\/be139bf0-ab0f-11ef-b429-5b139d1e7a7e.jpg","audio":""},{"link":"https:\/\/www.entertainmentdaily.com\/tv\/im-a-celebrity-oti-mabuse-more-airtime-plea-fans\/","title":"I\u2019m A Celebrity viewers beg bosses to give Oti Mabuse \u2018more airtime\u2019","ch":"Entertainment Daily","date":1732544014,"image":"https:\/\/cdn.entertainmentdaily.com\/2021\/01\/25101916\/cropped-logo-512-32x32.png","audio":""},{"link":"https:\/\/www.youtube.com\/watch?v=pLqejT94HaA","title":"I\u2019m A Celebrity: Jane\u2019s Sexism Row and Maura\u2019s Revenge on Ex | Loose Women","ch":"Loose Women","date":1732540860,"image":"https:\/\/i1.ytimg.com\/vi\/pLqejT94HaA\/hqdefault.jpg","audio":""},{"link":"https:\/\/www.entertainmentdaily.com\/tv\/dianne-buswell-strictly-dad-upset-secret\/","title":"Strictly star Dianne Buswell admits her dad will be \u2018upset\u2019 as she recalls family memory","ch":"Entertainment Daily","date":1732540071,"image":"https:\/\/cdn.entertainmentdaily.com\/2021\/01\/25101916\/cropped-logo-512-32x32.png","audio":""},{"link":"https:\/\/www.entertainmentdaily.com\/tv\/im-a-celebrity-ant-and-dec-unfair-jane-moore-sexism-row\/","title":"I\u2019m A Celebrity hosts Ant and Dec hit out at \u2018unfair\u2019 Jane Moore over \u2018sexism\u2019 row","ch":"Entertainment Daily","date":1732539829,"image":"https:\/\/cdn.entertainmentdaily.com\/2021\/01\/25101916\/cropped-logo-512-32x32.png","audio":""},{"link":"https:\/\/www.vanityfair.com\/style\/photos\/24-fabulous-gifts-inspired-by-the-wiz","title":"24 Gifts Inspired by \u2018The Wiz,\u2019 for Oz Lovers and \u2018Wicked\u2019 Fans and Bears, Oh My!","ch":"Vanity Fair","date":1732539600,"image":"https:\/\/media.vanityfair.com\/photos\/672e5a6782ac43960d53ba21\/master\/pass\/VF1224-Gift-Guide-The-Wiz-Tout.png","audio":""},{"link":"https:\/\/www.bbc.com\/news\/articles\/cgl47ne8g9po","title":"Davina McCall says 'it's nice to be home' after brain surgery","ch":"BBC News","date":1732526780,"image":"https:\/\/ichef.bbci.co.uk\/ace\/standard\/240\/cpsprodpb\/b7bf\/live\/dc67d4a0-ab45-11ef-8ab9-9192db313061.jpg","audio":""},{"link":"https:\/\/www.bbc.com\/news\/articles\/c4gprpzdylno","title":"Wicked proves popular as opening set to be biggest for Broadway film","ch":"BBC News","date":1732484381,"image":"https:\/\/ichef.bbci.co.uk\/ace\/standard\/240\/cpsprodpb\/4f69\/live\/aed23300-aad2-11ef-bdf5-b7cb2fa86e10.jpg","audio":""},{"link":"https:\/\/www.vanityfair.com\/news\/story\/elon-musk-jokes-msnbc-purchase","title":"Elon Musk Muses About Buying MSNBC: \u201cHow Much Does It Cost?\u201d","ch":"Vanity Fair","date":1732476310,"image":"https:\/\/media.vanityfair.com\/photos\/674374daba2e166bad9d4783\/master\/pass\/2179030530","audio":""},{"link":"https:\/\/www.bbc.com\/news\/articles\/c62l15qz521o","title":"Feel free to sing in the cinema, says The Rock","ch":"BBC News","date":1732470933,"image":"https:\/\/ichef.bbci.co.uk\/ace\/standard\/240\/cpsprodpb\/fac1\/live\/540dbd10-aa8a-11ef-9325-79c3284cf7e7.jpg","audio":""},{"link":"https:\/\/www.vanityfair.com\/hollywood\/story\/taylor-swift-toronto-eras-tour-crying","title":"Taylor Swift Near Tears as Eras Tour Approaches End","ch":"Vanity Fair","date":1732468365,"image":"https:\/\/media.vanityfair.com\/photos\/674350b5ba2e166bad9d4781\/master\/pass\/2178464297","audio":""},{"link":"https:\/\/www.vanityfair.com\/hollywood\/story\/the-taylor-swift-travis-kelce-inspired-lifetime-movie-easter-eggs","title":"The Taylor Swift\/Travis Kelce-Inspired Lifetime Movie Is One Giant Easter Egg","ch":"Vanity Fair","date":1732417260,"image":"https:\/\/media.vanityfair.com\/photos\/6740af91b579d2bda4ee98c6\/master\/pass\/vf1124-lifetime-taylor-swift.jpg","audio":""},{"link":"https:\/\/www.vanityfair.com\/news\/story\/trump-went-on-an-appointing-spree","title":"President-Elect Donald Trump Went On An Appointing Spree Friday Night","ch":"Vanity Fair","date":1732390846,"image":"https:\/\/media.vanityfair.com\/photos\/67422618c7371594e8ac9bc7\/master\/pass\/2183887435","audio":""},{"link":"https:\/\/www.youtube.com\/watch?v=ShXWyMTcnok","title":"Craig Revel Horwood: 'I Recorded an Album as a Gift to My Mum' | Loose Women","ch":"Loose Women","date":1732285813,"image":"https:\/\/i4.ytimg.com\/vi\/ShXWyMTcnok\/hqdefault.jpg","audio":""},{"link":"https:\/\/www.youtube.com\/watch?v=_nv6orttcUc","title":"I\u2019m A Celebrity: Rooney the Romantic & Contraband Controversy | Loose Women","ch":"Loose Women","date":1732282074,"image":"https:\/\/i4.ytimg.com\/vi\/_nv6orttcUc\/hqdefault.jpg","audio":""},{"link":"https:\/\/vipmagazine.ie\/well-known-faces-step-out-for-dylan-oakes-shop-opening\/","title":"Well known faces step out for Dylan Oakes shop opening","ch":"VIP Magazine","date":1732279615,"image":"https:\/\/vip-uploads.s3.amazonaws.com\/uploads\/2019\/09\/favicon-vip.png","audio":""},{"link":"https:\/\/vipmagazine.ie\/ageing-gracefully-the-skincare-guide-to-over-50\/","title":"Ageing gracefully: The skincare guide to over 50","ch":"VIP Magazine","date":1732277449,"image":"https:\/\/vip-uploads.s3.amazonaws.com\/uploads\/2019\/09\/favicon-vip.png","audio":""},{"link":"https:\/\/vipmagazine.ie\/singer-songwriter-aimee-on-life-in-la-chasing-dreams-and-family-values\/","title":"Singer-songwriter Aimee on life in LA, chasing dreams and family values","ch":"VIP Magazine","date":1732276939,"image":"https:\/\/vip-uploads.s3.amazonaws.com\/uploads\/2019\/09\/favicon-vip.png","audio":""},{"link":"https:\/\/vipmagazine.ie\/what-is-blonzing-the-latest-beauty-trend-that-is-taking-over\/","title":"What is Blonzing? The latest beauty trend that is taking over","ch":"VIP Magazine","date":1732276653,"image":"https:\/\/vip-uploads.s3.amazonaws.com\/uploads\/2019\/09\/favicon-vip.png","audio":""}]