[{"link":"https:\/\/www.hellomagazine.com\/film\/727987\/savannah-guthrie-supported-by-fans-today-show-difficult-week\/","title":"Savannah Guthrie supported by fans as Today hosts discuss difficult week ahead","ch":"HELLO! Latest news feed","date":1730737535,"image":"","audio":""},{"link":"https:\/\/www.hellomagazine.com\/homes\/727968\/king-charles-and-queen-camillas-unique-sleeping-arrangements-in-private-royal-homes\/","title":"King Charles and Queen Camilla's unique sleeping arrangements in private royal homes","ch":"HELLO! Latest news feed","date":1730737355,"image":"","audio":""},{"link":"https:\/\/www.hellomagazine.com\/brides\/727980\/ben-affleck-breaks-silence-jennifer-lopez-divorce-what-he-said\/","title":"Ben Affleck finally breaks silence on Jennifer Lopez amid divorce \u2014 and here's what he had to say","ch":"HELLO! Latest news feed","date":1730737262,"image":"","audio":""},{"link":"https:\/\/www.hellomagazine.com\/hfm\/wish-list\/727937\/bonfire-night-easy-outfits\/","title":"Bonfire Night: 5 easy outfits that serve up cosy-chic","ch":"HELLO! Latest news feed","date":1730737231,"image":"","audio":""},{"link":"https:\/\/www.entertainmentdaily.com\/news\/peter-andre-emily-sadness-missing-out-family-milestones\/","title":"Peter Andre addresses \u2018missing\u2019 out on family milestones: \u2018It\u2019s not fair on Emily\u2019","ch":"Entertainment Daily","date":1730736775,"image":"https:\/\/cdn.entertainmentdaily.com\/2021\/01\/25101916\/cropped-logo-512-32x32.png","audio":""},{"link":"https:\/\/www.hellomagazine.com\/hfm\/wish-list\/727975\/best-suede-bags\/","title":"10 Suede bags that will make every outfit look expensive","ch":"HELLO! Latest news feed","date":1730736406,"image":"","audio":""},{"link":"https:\/\/www.youtube.com\/watch?v=mHXFcN7u6j8","title":"Shocking True Crime Podcast Exposes Hitman Hiring Website | Loose Women","ch":"Loose Women","date":1730736043,"image":"https:\/\/i2.ytimg.com\/vi\/mHXFcN7u6j8\/hqdefault.jpg","audio":""},{"link":"https:\/\/www.entertainmentdaily.com\/tv\/strictly-chris-mccausland-explains-down-appearance-results-show\/","title":"Strictly star Chris McCausland explains \u2018down\u2019 appearance on results show","ch":"Entertainment Daily","date":1730735337,"image":"https:\/\/cdn.entertainmentdaily.com\/2021\/01\/25101916\/cropped-logo-512-32x32.png","audio":""},{"link":"https:\/\/www.bbc.com\/news\/articles\/cjr4n2490r9o","title":"Quincy Jones, giant of US music, has died aged 91","ch":"BBC News","date":1730734894,"image":"https:\/\/ichef.bbci.co.uk\/ace\/standard\/240\/cpsprodpb\/6c1c\/live\/2b609e70-9a9d-11ef-82c3-45a801b7330b.jpg","audio":""},{"link":"https:\/\/www.vanityfair.com\/hollywood\/story\/james-van-der-beek-announces-he-has-colorectal-cancer","title":"James Van Der Beek Announces He Has Colorectal Cancer","ch":"Vanity Fair","date":1730734009,"image":"https:\/\/media.vanityfair.com\/photos\/6728e6fca84d0a300d306de8\/master\/pass\/1580558620","audio":""},{"link":"https:\/\/www.vanityfair.com\/style\/story\/celebrity-endorsements-harris-trump","title":"Who Has Endorsed Kamala Harris\u2014or Donald Trump? A Running List of Celebrity Endorsements","ch":"Vanity Fair","date":1730733992,"image":"https:\/\/media.vanityfair.com\/photos\/66eb3f9175bbd50011882f8c\/master\/pass\/kamala-harris-donald-trump-celeb-endorsements.jpg","audio":""},{"link":"https:\/\/www.entertainmentdaily.com\/news\/my-mum-your-dad-star-janey-roger-plans-foster\/","title":"My Mum, Your Dad star Janey reveals desire to foster a child with Roger a year on from show","ch":"Entertainment Daily","date":1730733314,"image":"https:\/\/cdn.entertainmentdaily.com\/2021\/01\/25101916\/cropped-logo-512-32x32.png","audio":""},{"link":"https:\/\/www.youtube.com\/watch?v=sAq_OJKPIKc","title":"Myleene Details 'Grief and Shame' of Four Miscarriages | Loose Women","ch":"Loose Women","date":1730732453,"image":"https:\/\/i4.ytimg.com\/vi\/sAq_OJKPIKc\/hqdefault.jpg","audio":""},{"link":"https:\/\/vipmagazine.ie\/my-beauty-bag-with-charlene-flanagan\/","title":"My Beauty Bag with Charlene Flanagan","ch":"VIP Magazine","date":1730732065,"image":"https:\/\/vip-uploads.s3.amazonaws.com\/uploads\/2019\/09\/favicon-vip.png","audio":""},{"link":"https:\/\/www.entertainmentdaily.com\/tv\/strictly-shirley-ballas-hits-back-childish-criticism-latest-elimination\/","title":"Strictly judge Shirley Ballas hits back as she blasts \u2018childish\u2019 criticism following latest elimination","ch":"Entertainment Daily","date":1730730579,"image":"https:\/\/cdn.entertainmentdaily.com\/2021\/01\/25101916\/cropped-logo-512-32x32.png","audio":""},{"link":"https:\/\/www.youtube.com\/watch?v=5-PIcsA580c","title":"US Election: Does Your Partner Influence Your Vote? | Loose Women","ch":"Loose Women","date":1730728650,"image":"https:\/\/i2.ytimg.com\/vi\/5-PIcsA580c\/hqdefault.jpg","audio":""},{"link":"https:\/\/www.entertainmentdaily.com\/tv\/strictly-shirley-ballas-attacks-craig-revel-horwood-johannes-radebe-anger\/","title":"Strictly star Johannes Radebe\u2019s \u2018anger\u2019 as Shirley Ballas clashes with Craig Revel Horwood live on air","ch":"Entertainment Daily","date":1730726485,"image":"https:\/\/cdn.entertainmentdaily.com\/2021\/01\/25101916\/cropped-logo-512-32x32.png","audio":""},{"link":"https:\/\/www.bbc.com\/news\/articles\/c4gz3w38dn9o","title":"Quincy Jones: His brilliance explained in 10 songs ","ch":"BBC News","date":1730726450,"image":"https:\/\/ichef.bbci.co.uk\/ace\/standard\/240\/cpsprodpb\/f18a\/live\/debe1e40-9abe-11ef-82c3-45a801b7330b.jpg","audio":""},{"link":"https:\/\/vipmagazine.ie\/roz-purcell-celebrates-sister-rachels-wedding-day\/","title":"Roz Purcell celebrates sister Rachel\u2019s wedding day","ch":"VIP Magazine","date":1730725461,"image":"https:\/\/vip-uploads.s3.amazonaws.com\/uploads\/2019\/09\/favicon-vip.png","audio":""},{"link":"https:\/\/www.vanityfair.com\/hollywood\/story\/kate-winslet-in-conversation-lee-awards-insider","title":"Kate Winslet Is Fighting for Her Passion Project: \u201cDo You Have Any Idea How F--king Hard It Is?\u201d","ch":"Vanity Fair","date":1730725200,"image":"https:\/\/media.vanityfair.com\/photos\/672128cd0344298284726553\/master\/pass\/vf1024-kate-winslet.jpg","audio":""},{"link":"https:\/\/vipmagazine.ie\/colm-meaney-and-paul-reiser-walk-dublin-red-carpet\/","title":"Colm Meaney and Paul Reiser walk Dublin red carpet","ch":"VIP Magazine","date":1730724044,"image":"https:\/\/vip-uploads.s3.amazonaws.com\/uploads\/2019\/09\/favicon-vip.png","audio":""},{"link":"https:\/\/www.vanityfair.com\/style\/story\/music-impresario-quincy-jones-91-is-dead","title":"Music Impresario Quincy Jones, 91, Is Dead","ch":"Vanity Fair","date":1730723187,"image":"https:\/\/media.vanityfair.com\/photos\/6728bbf2a84d0a300d306de3\/master\/pass\/517428034","audio":""},{"link":"https:\/\/vipmagazine.ie\/ageing-gracefully-the-skincare-guide-to-over-50\/","title":"Ageing gracefully: The skincare guide to over 50","ch":"VIP Magazine","date":1730723149,"image":"https:\/\/vip-uploads.s3.amazonaws.com\/uploads\/2019\/09\/favicon-vip.png","audio":""},{"link":"https:\/\/www.bbc.com\/news\/articles\/c62987ve81zo","title":"Selena Gomez was 'more nervous than ever' for new musical role","ch":"BBC News","date":1730721053,"image":"https:\/\/ichef.bbci.co.uk\/ace\/standard\/240\/cpsprodpb\/1f20\/live\/e83176f0-9aa2-11ef-9de3-77af1057b5da.jpg","audio":""},{"link":"https:\/\/vipmagazine.ie\/i-worry-about-that-constantly-louise-mcsharry-on-parenting-her-children-openly-in-a-digital-age\/","title":"\u201cI worry about that constantly!\u201d: Louise McSharry on parenting her children openly in a digital age","ch":"VIP Magazine","date":1730720124,"image":"https:\/\/vip-uploads.s3.amazonaws.com\/uploads\/2019\/09\/favicon-vip.png","audio":""},{"link":"https:\/\/www.bbc.com\/news\/articles\/c8ek6kjygdjo","title":"Strictly stars celebrate 'glitterball'  Windsor","ch":"BBC News","date":1730710294,"image":"https:\/\/ichef.bbci.co.uk\/ace\/standard\/240\/cpsprodpb\/75c3\/live\/ff6893b0-9a8b-11ef-959c-8372cc6170d3.jpg","audio":""},{"link":"https:\/\/www.vanityfair.com\/style\/story\/queen-camilla-documentary-domestic-violence","title":"Queen Camilla Teams Up with All-Female Crew for Documentary About Domestic Violence","ch":"Vanity Fair","date":1730682000,"image":"https:\/\/media.vanityfair.com\/photos\/6727d108bfef095ebd706849\/master\/pass\/2178987384","audio":""},{"link":"https:\/\/www.bbc.com\/news\/articles\/c4gmrn0mxrno","title":"Dawson's Creek actor reveals cancer diagnosis ","ch":"BBC News","date":1730678905,"image":"https:\/\/ichef.bbci.co.uk\/ace\/standard\/240\/cpsprodpb\/1f74\/live\/6cf4b860-9a3b-11ef-9caf-ad4648846c79.jpg","audio":""},{"link":"https:\/\/www.youtube.com\/watch?v=cuu0pdcuvzg","title":"Real Housewives Host Andy Cohen Turned Down Meghan Markle | Loose Women","ch":"Loose Women","date":1730480437,"image":"https:\/\/i4.ytimg.com\/vi\/cuu0pdcuvzg\/hqdefault.jpg","audio":""},{"link":"https:\/\/www.youtube.com\/watch?v=lLGMPGIQoL0","title":"Will My Sex Life Be Ruined If He Watches Me Give Birth? | Loose Women","ch":"Loose Women","date":1730473255,"image":"https:\/\/i1.ytimg.com\/vi\/lLGMPGIQoL0\/hqdefault.jpg","audio":""}]